LICENSE
setup.py
cuth/Cuth.py
cuth/CuthConfiger.py
cuth/__init__.py
cuth.egg-info/PKG-INFO
cuth.egg-info/SOURCES.txt
cuth.egg-info/dependency_links.txt
cuth.egg-info/requires.txt
cuth.egg-info/top_level.txt